lsfb_dataset/__init__.py
lsfb_dataset/datasets/__init__.py
lsfb_dataset/datasets/lsfb_cont/__init__.py
lsfb_dataset/datasets/lsfb_cont/base.py
lsfb_dataset/datasets/lsfb_cont/config.py
lsfb_dataset/datasets/lsfb_cont/landmarks.py
lsfb_dataset/datasets/lsfb_cont/landmarks_generator.py
lsfb_dataset/datasets/lsfb_isol/__init__.py
lsfb_dataset/datasets/lsfb_isol/base.py
lsfb_dataset/datasets/lsfb_isol/config.py
lsfb_dataset/datasets/lsfb_isol/landmarks.py
lsfb_dataset/datasets/lsfb_isol/landmarks_generator.py
lsfb_dataset/download/__init__.py
lsfb_dataset/download/downloader.py
lsfb_dataset/utils/__init__.py
lsfb_dataset/utils/datasets.py
lsfb_dataset-2.0.1.dist-info/LICENSE
lsfb_dataset-2.0.1.dist-info/METADATA
lsfb_dataset-2.0.1.dist-info/WHEEL
lsfb_dataset-2.0.1.dist-info/top_level.txt
lsfb_dataset-2.0.1.dist-info/RECORD
