Metadata-Version: 2.1
Name: lsfb-dataset
Version: 2.0.1
Summary: A companion library for the LSFB-dataset
Home-page: https://github.com/LSFB-Team/lsfb-dataset
Author: Jérôme Fink, Poitier Pierre
Author-email: jerome.fink@unamur.be, pierre.poitier@unamur.be
Project-URL: Bug Tracker, https://github.com/LSFB-Team/lsfb-dataset/issues
Project-URL: Documentation, https://lsfb-team.github.io/lsfb-dataset/
Classifier: Programming Language :: Python :: 3
Classifier: License :: OSI Approved :: MIT License
Classifier: Operating System :: OS Independent
Requires-Python: >=3.9
License-File: LICENSE
Requires-Dist: numpy
Requires-Dist: pandas
Requires-Dist: tqdm
Requires-Dist: requests
